codeprint/__init__.py
codeprint/cli.py
codeprintio-1.0.7.dist-info/licenses/LICENSE
codeprintio-1.0.7.dist-info/METADATA
codeprintio-1.0.7.dist-info/WHEEL
codeprintio-1.0.7.dist-info/entry_points.txt
codeprintio-1.0.7.dist-info/top_level.txt
codeprintio-1.0.7.dist-info/RECORD
