Metadata-Version: 2.4
Name: codeprintio
Version: 1.0.7
Summary: A powerful cross-platform tool for creating AI-ready project snapshots
Author-email: Tanay Kedia <tkedia7@gmail.com>
License: MIT
Project-URL: Homepage, https://github.com/Tanayk07/codeprint
Project-URL: Bug Tracker, https://github.com/Tanayk07/codeprint/issues
Project-URL: Documentation, https://github.com/Tanayk07/codeprint#readme
Classifier: Development Status :: 5 - Production/Stable
Classifier: Intended Audience :: Developers
Classifier: Topic :: Software Development :: Documentation
Classifier: Programming Language :: Python :: 3
Classifier: Programming Language :: Python :: 3.7
Classifier: Programming Language :: Python :: 3.8
Classifier: Programming Language :: Python :: 3.9
Classifier: Programming Language :: Python :: 3.10
Classifier: Programming Language :: Python :: 3.11
Classifier: Programming Language :: Python :: 3.12
Classifier: Operating System :: OS Independent
Requires-Python: >=3.7
License-File: LICENSE
Requires-Dist: colorama>=0.4.4
Requires-Dist: pyperclip>=1.8.2
Provides-Extra: dev
Requires-Dist: pytest>=7.0.0; extra == "dev"
Requires-Dist: pytest-cov>=3.0.0; extra == "dev"
Requires-Dist: black>=22.0.0; extra == "dev"
Requires-Dist: flake8>=4.0.0; extra == "dev"
Requires-Dist: mypy>=0.950; extra == "dev"
Dynamic: license-file
